cyclomatic_complexity/__init__.py
cyclomatic_complexity/main.py
yangwangjinxin_cyclomatic_complexity-0.0.3.dist-info/LICENSE
yangwangjinxin_cyclomatic_complexity-0.0.3.dist-info/METADATA
yangwangjinxin_cyclomatic_complexity-0.0.3.dist-info/WHEEL
yangwangjinxin_cyclomatic_complexity-0.0.3.dist-info/top_level.txt
yangwangjinxin_cyclomatic_complexity-0.0.3.dist-info/RECORD
