Metadata-Version: 2.1
Name: yangwangjinxin-cyclomatic-complexity
Version: 0.0.3
Summary: cyclomatic complexity
Author-email: yangwangjinxing <yangwangjinxing@163.com>
License: Copyright (c) 2018 The Python Packaging Authority        
Project-URL: Homepage, https://github.com/yangwangjinxing/cyclomatic_complexity
Project-URL: Bug Tracker, https://github.com/yangwangjinxing/cyclomatic_complexity/issues
Classifier: Programming Language :: Python :: 3
Classifier: License :: OSI Approved :: MIT License
Classifier: Operating System :: OS Independent
Requires-Python: >=3.7
License-File: LICENSE
Requires-Dist: lizard (<2,>=1.17.0)
